kutty/__init__.py
kutty/cleaning.py
kutty/timeseries.py
kutty/visualization.py
kutty-0.2.4.dist-info/METADATA
kutty-0.2.4.dist-info/WHEEL
kutty-0.2.4.dist-info/RECORD
