Metadata-Version: 2.1
Name: kutty
Version: 0.2.4
Summary: 
Author: kuttykishore
Author-email: kishorekumar.mourougane@epita.fr
Requires-Python: >=3.7
Classifier: Programming Language :: Python :: 3
Classifier: Programming Language :: Python :: 3.7
Classifier: Programming Language :: Python :: 3.8
Classifier: Programming Language :: Python :: 3.9
Classifier: Programming Language :: Python :: 3.10
Classifier: Programming Language :: Python :: 3.11
Classifier: Programming Language :: Python :: 3.12
Requires-Dist: numpy (>=1.19,<2.0)
Requires-Dist: pandas (>=1.2,<2.0)
Requires-Dist: plotly (>=4.9,<5.0)
Requires-Dist: scipy (>=1.5,<2.0)
